Metadata-Version: 1.0
Name: probabs
Version: 1.0
Summary: Gaussian and Binomial distributions
Home-page: UNKNOWN
Author: Ankur Chourasia
Author-email: chourasia.ankur1@gmail.com
License: UNKNOWN
Platform: UNKNOWN
